<annotation>
	<folder>video_screenshots</folder>
	<filename>video_15.jpg</filename>
	<path>C:\Users\Siri\Desktop\BARC_ki_padhai\Project\video_screenshots\video_15.jpg</path>
	<source>
		<database>Unknown</database>
	</source>
	<size>
		<width>924</width>
		<height>526</height>
		<depth>3</depth>
	</size>
	<segmented>0</segmented>
	<object>
		<name>MH01CP2655</name>
		<pose>Unspecified</pose>
		<truncated>0</truncated>
		<difficult>0</difficult>
		<bndbox>
			<xmin>376</xmin>
			<ymin>62</ymin>
			<xmax>846</xmax>
			<ymax>234</ymax>
		</bndbox>
	</object>
</annotation>
